{
"type": "FeatureCollection",
"crs": { "type": "name", "properties": { "name": "urn:ogc:def:crs:OGC:1.3:CRS84" } },
                                                                                
"features": [
{ "type": "Feature", "properties": { "cat": 1, "x": -84.19, "y": 10.34, "value": 4 }, "geometry": { "type": "Point", "coordinates": [ -84.19, 10.34 ] } },
{ "type": "Feature", "properties": { "cat": 2, "x": -84.73, "y": 10.57, "value": 5 }, "geometry": { "type": "Point", "coordinates": [ -84.73, 10.57 ] } },
{ "type": "Feature", "id": -1294967293, "properties": { "cat": 3, "x": -84.42, "y": 10.19, "value": 2 }, "geometry": { "type": "Point", "coordinates": [ -84.42, 10.19 ] } },
{ "type": "Feature", "id": -294967292, "properties": { "cat": 4, "x": -84.27, "y": 10.34, "value": 4 }, "geometry": { "type": "Point", "coordinates": [ -84.27, 10.34 ] } },
{ "type": "Feature", "id": 705032709, "properties": { "cat": 5, "x": -84.09, "y": 10.26, "value": 7 }, "geometry": { "type": "Point", "coordinates": [ -84.09, 10.26 ] } },
{ "type": "Feature", "id": 1705032710, "properties": { "cat": 6, "x": -84.29, "y": 10.43, "value": 4 }, "geometry": { "type": "Point", "coordinates": [ -84.29, 10.43 ] } },
{ "type": "Feature", "id": -1589934585, "properties": { "cat": 7, "x": -84.37, "y": 10.75, "value": 2 }, "geometry": { "type": "Point", "coordinates": [ -84.37, 10.75 ] } },
{ "type": "Feature", "id": -589934584, "properties": { "cat": 8, "x": -84.24, "y": 10.91, "value": 1 }, "geometry": { "type": "Point", "coordinates": [ -84.24, 10.91 ] } },
{ "type": "Feature", "id": 410065417, "properties": { "cat": 9, "x": -84.72, "y": 10.43, "value": 5 }, "geometry": { "type": "Point", "coordinates": [ -84.72, 10.43 ] } }
]
}
